app_executor/__init__.py
app_executor/app_executor.py
app_executor/conftest.py
app_executor/process.py
app_executor/tests/__init__.py
app_executor/tests/test_app_executor.py
app_executor/tests/test_process.py
app_executor-1.0.0.dist-info/METADATA
app_executor-1.0.0.dist-info/WHEEL
app_executor-1.0.0.dist-info/entry_points.txt
app_executor-1.0.0.dist-info/top_level.txt
app_executor-1.0.0.dist-info/RECORD
