Metadata-Version: 2.1
Name: app-executor
Version: 1.0.0
Summary: Tool for safe launching external processes
Home-page: https://github.com/pasiasty/app-executor
Author: Mariusz Pasek
Author-email: pasiasty@gmail.com
License: UNKNOWN
Platform: UNKNOWN
Classifier: Programming Language :: Python :: 3
Classifier: License :: OSI Approved :: MIT License
Classifier: Operating System :: OS Independent
Requires-Dist: atomicwrites (==1.3.0)
Requires-Dist: attrs (==18.2.0)
Requires-Dist: more-itertools (==6.0.0)
Requires-Dist: pluggy (==0.9.0)
Requires-Dist: py (==1.8.0)
Requires-Dist: pytest (==4.3.0)
Requires-Dist: six (==1.12.0)
